{
  "book": [
    {
      "features": [
        {
          "type": "FeatureImage",
          "properties": {
            "path": "Welcome_Book/title.png",
            "xPos": 12,
            "yPos": 45,
            "width": 204.0,
            "height": 105.0
          }
        },
        {
          "type": "FeatureText",
          "properties": {
            "text": "Welcome To Another Way To Start",
            "wrap": 0,
            "size": 1.0,
            "color": "FFFF0000",
            "xPos": 32,
            "yPos": 24,
            "width": 181.0,
            "height": 13.0
          }
        },
        {
          "type": "FeatureText",
          "properties": {
            "text": "Version : 1.2.9",
            "wrap": 0,
            "size": 1.0,
            "color": "FF0000FF",
            "xPos": 79,
            "yPos": 172,
            "width": 178.0,
            "height": 27.0
          }
        },
        {
          "type": "FeatureImage",
          "properties": {
            "path": "Welcome_Book/BigRice1018.png",
            "xPos": 204,
            "yPos": 30,
            "width": 90.0,
            "height": 93.0
          }
        },
        {
          "type": "FeatureText",
          "properties": {
            "text": "Developers",
            "wrap": 0,
            "size": 1.0,
            "color": "FFFF0000",
            "xPos": 290,
            "yPos": 16,
            "width": 55.0,
            "height": 11.0
          }
        },
        {
          "type": "FeatureBox",
          "properties": {
            "color": "",
            "xPos": -7,
            "yPos": 203,
            "width": 49.0,
            "height": 69.0
          }
        },
        {
          "type": "FeatureImage",
          "properties": {
            "path": "Welcome_Book/livedomo520.png",
            "xPos": 342,
            "yPos": 34,
            "width": 65.0,
            "height": 65.0
          }
        },
        {
          "type": "FeatureImage",
          "properties": {
            "path": "Welcome_Book/yjo4nk45m3.png",
            "xPos": 276,
            "yPos": 33,
            "width": 69.0,
            "height": 67.0
          }
        },
        {
          "type": "FeatureText",
          "properties": {
            "text": "BigRice1018        (BigRice)\n\n  All stuff",
            "wrap": 0,
            "size": 1.0,
            "color": "FFFF8C00",
            "xPos": 220,
            "yPos": 126,
            "width": 74.0,
            "height": 45.0
          }
        },
        {
          "type": "FeatureText",
          "properties": {
            "text": "yjo4nk45m3 \n (Chifung)\n               \n    Logo \n Ingot Unify",
            "wrap": 0,
            "size": 1.0,
            "color": "FF0000CD",
            "xPos": 282,
            "yPos": 104,
            "width": 78.0,
            "height": 47.0
          }
        },
        {
          "type": "FeatureText",
          "properties": {
            "text": "livedomo520    (Wendy)\n\n  Ore Gen",
            "wrap": 0,
            "size": 1.0,
            "color": "FFF08080",
            "xPos": 346,
            "yPos": 104,
            "width": 62.0,
            "height": 43.0
          }
        },
        {
          "type": "FeatureText",
          "properties": {
            "text": "Also big thanks for all the mods authors for their cool mods.\nAnother thanks for all the beta testers.",
            "wrap": 0,
            "size": 1.0,
            "color": "FF191970",
            "xPos": 223,
            "yPos": 170,
            "width": 189.0,
            "height": 28.0
          }
        },
        {
          "type": "FeatureJump",
          "properties": {
            "jumpTo": "2",
            "texture": "",
            "xPos": 0,
            "yPos": 0,
            "width": 435.0,
            "height": 221.0
          }
        }
      ],
      "pageName": ""
    },
    {
      "features": [
        {
          "type": "FeatureImage",
          "properties": {
            "path": "Welcome_Book/mindmap.png",
            "xPos": 23,
            "yPos": 1,
            "width": 357.0,
            "height": 210.0
          }
        },
        {
          "type": "FeatureJump",
          "properties": {
            "jumpTo": "\n\n",
            "texture": "",
            "xPos": -106,
            "yPos": -52,
            "width": 632.0,
            "height": 336.0
          }
        }
      ],
      "pageName": ""
    },
    {
      "features": [
        {
          "type": "FeatureImage",
          "properties": {
            "path": "Welcome_Book/Screenshot_7.png",
            "xPos": -14,
            "yPos": -70,
            "width": 458.0,
            "height": 127.0
          }
        },
        {
          "type": "FeatureImage",
          "properties": {
            "path": "Welcome_Book/Screenshot_6.png",
            "xPos": -8,
            "yPos": 57,
            "width": 453.0,
            "height": 215.0
          }
        },
        {
          "type": "FeatureJump",
          "properties": {
            "jumpTo": "1",
            "texture": "",
            "xPos": -95,
            "yPos": -62,
            "width": 622.0,
            "height": 345.0
          }
        }
      ],
      "pageName": ""
    }
  ],
  "uniqueName": "Welcome_Book",
  "color": 16777215,
  "showBackground": true,
  "showArrows": false,
  "showNumber": false,
  "iconPass1": "",
  "iconPass2": "",
  "iconColorisePass1": false,
  "iconColorisePass2": false,
  "iconColorPass1": 0,
  "iconColorPass2": 0,
  "language": "en_US",
  "displayName": "Welcome_Book",
  "displayInCreative": true
}